{
  "settings": [],
 "dependencies": {
    "R": [
      {
        "name": "move"
      },
      {
        "name": "lubridate"
      },
      {
        "name": "amt"
      },
      {
        "name": "purrr"
      },
      {
        "name": "reshape2"
      },
      {
        "name": "ggplot2"
      },
      {
        "name": "ggforce"
      },
      {
        "name": "leaflet"
      },
      {
        "name": "RColorBrewer"
      },
      {
        "name": "mapview"
      },
      {
        "name": "sf"
      },
      {
        "name": "zip"
      }
    ]
  },
  "createsArtifacts": true,
  "license": {
    "key": "MIT"
  },
  "language": "eng",
  "keywords": [
    "space use",
    "KDE"
  ],
  "people": [
    {
      "firstName": "Varalika",
      "middleInitials": null,
      "lastName": "Jain",
      "email": "varalika.jain@univie.ac.at",
      "roles": [
        "author",
        "creator"
      ],
      "orcid": "0000-0002-4809-9551",
      "affiliation": "University of Vienna",
      "affiliationRor": null
    }
  ],
  "funding": [],
    "references": [
    {
      "type": "IsDescribedBy",
      "note": "Signer J., Fieberg J., Avgar T. (2011). Animal movement tools (amt): R package for managing tracking data and conducting habitat selection analyses. Ecology and Evolution 2019 9, 880-890.",
      "url": "https://doi.org/10.1002/ece3.4823"
    }
  ],
  "documentation": {
    "url": "https://github.com/vee-jain/WeeklyKDE-MoveApps/blob/main/README.md"
  }
}
